Workbook
Name SegmentaçãodeDados_Department: #N/A
Name SegmentaçãodeDados_Gender: #N/A
Name SegmentaçãodeDados_State: #N/A

Sheet HumanResource
A1: Employee_ID,First Name,Last Name,Gender,State,City,Education Level,Birthdate,Hiredate,Termdate,Department,Job Title,Salary,Performance Rating
A2: 00-95822412,Danielle,Johnson,Female,New York,New York City,High School,13/02/1980,16/04/2016,5/7/2021,Customer Service,Help Desk Technician,81552,Needs Improvement
A3: 00-42868828,John,Taylor,Male,North Carolina,Charlotte,Bachelor,22/09/1987,9/2/2017,14/06/2019,IT,System Administrator,107520,Good
A4: 00-83197857,Erica,Mcclain,Male,New York,New York City,Bachelor,19/05/1994,3/2/2016,6/3/2021,Operations,Logistics Coordinator,61104,Good
A5: 00-13999315,Brittany,Johnson,Male,New York,New York City,Bachelor,18/04/1980,6/2/2016,6/11/2018,Operations,Inventory Specialist,73770,Good
A6: 00-90801586,Jeffery,Wagner,Female,New York,New York City,Bachelor,7/4/1985,11/1/2015,,Operations,Operations Analyst,55581,Satisfactory
A7: 00-97226012,Anna,Baldwin,Female,New York,New York City,Bachelor,31/05/1988,30/09/2022,29/03/2023,Operations,Operations Analyst,73800,Good
A8: 00-70291817,Amy,Robinson,Male,New York,New York City,Bachelor,16/07/1991,16/08/2020,12/2/2021,Finance,Accountant,68181,Good
A9: 00-31429110,Joshua,Booth,Female,New York,New York City,Bachelor,19/09/1995,22/10/2022,20/04/2023,Finance,Accounts Payable Specialist,54499,Good
A10: 00-30868105,Linda,Wolfe,Male,New York,New York City,High School,11/5/2002,13/05/2017,15/11/2021,Operations,Inventory Specialist,57340,Needs Improvement
A11: 00-22448136,Joshua,Lewis,Female,New York,New York City,Bachelor,21/11/1980,24/10/2018,30/03/2022,Operations,Logistics Coordinator,54065,Good
A12: 00-56164955,Matthew,Davis,Female,New York,New York City,High School,8/2/1994,7/2/2021,6/8/2021,Marketing,SEO Specialist,83262,Needs Improvement
... A8951: 00-50413766,Derek,Thornton,Female,New York,Rochester,PhD,4/8/1993,15/08/2017,,Sales,Sales Specialist,68351,Good

Sheet ADEQUAÇÃO
A1: Employee_ID | B1: First Name | C1: Last Name | D1: Gender | E1: State | F1: City | G1: Education Level | H1: Birthdate | I1: Hiredate | J1: Termdate | K1: Department | L1: Job Title | M1: Salary | N1: Performance Rating | O1: Tenure | P1: Turnover | Q1: Performance Score
A2: 00-95822412 | B2: Danielle | C2: Johnson | D2: Female | E2: New York | F2: New York City | G2: High School | H2: 29264 | I2: 42476 | J2: 44382 | K2: Customer Service | L2: Help Desk Technician | M2: 81552 | N2: Needs Improvement | O2: 9.9835616 | P2: =IF(J2<>"","DESLIGADO","ATIVO") -> DESLIGADO | Q2: =IF(N2="Excellent",5,IF(N2="Good",4,IF(N2="Satisfactory",3,0))) -> 0
A3: 00-42868828 | B3: John | C3: Taylor | D3: Male | E3: North Carolina | F3: Charlotte | G3: Bachelor | H3: 32042 | I3: 42775 | J3: 43630 | K3: IT | L3: System Administrator | M3: 107520 | N3: Good | O3: 9.1643836 | P3: =IF(J3<>"","DESLIGADO","ATIVO") -> DESLIGADO | Q3: =IF(N3="Excellent",5,IF(N3="Good",4,IF(N3="Satisfactory",3,0))) -> 4
A4: 00-83197857 | B4: Erica | C4: Mcclain | D4: Male | E4: New York | F4: New York City | G4: Bachelor | H4: 34473 | I4: 42403 | J4: 44261 | K4: Operations | L4: Logistics Coordinator | M4: 61104 | N4: Good | O4: 10.183562 | P4: =IF(J4<>"","DESLIGADO","ATIVO") -> DESLIGADO | Q4: =IF(N4="Excellent",5,IF(N4="Good",4,IF(N4="Satisfactory",3,0))) -> 4
A5: 00-13999315 | B5: Brittany | C5: Johnson | D5: Male | E5: New York | F5: New York City | G5: Bachelor | H5: 29329 | I5: 42406 | J5: 43410 | K5: Operations | L5: Inventory Specialist | M5: 73770 | N5: Good | O5: 10.175342 | P5: =IF(J5<>"","DESLIGADO","ATIVO") -> DESLIGADO | Q5: =IF(N5="Excellent",5,IF(N5="Good",4,IF(N5="Satisfactory",3,0))) -> 4
A6: 00-90801586 | B6: Jeffery | C6: Wagner | D6: Female | E6: New York | F6: New York City | G6: Bachelor | H6: 31144 | I6: 42015 | K6: Operations | L6: Operations Analyst | M6: 55581 | N6: Satisfactory | O6: 11.246575 | P6: =IF(J6<>"","DESLIGADO","ATIVO") -> ATIVO | Q6: =IF(N6="Excellent",5,IF(N6="Good",4,IF(N6="Satisfactory",3,0))) -> 3
A7: 00-97226012 | B7: Anna | C7: Baldwin | D7: Female | E7: New York | F7: New York City | G7: Bachelor | H7: 32294 | I7: 44834 | J7: 45014 | K7: Operations | L7: Operations Analyst | M7: 73800 | N7: Good | O7: 3.5232877 | P7: =IF(J7<>"","DESLIGADO","ATIVO") -> DESLIGADO | Q7: =IF(N7="Excellent",5,IF(N7="Good",4,IF(N7="Satisfactory",3,0))) -> 4
A8: 00-70291817 | B8: Amy | C8: Robinson | D8: Male | E8: New York | F8: New York City | G8: Bachelor | H8: 33435 | I8: 44059 | J8: 44239 | K8: Finance | L8: Accountant | M8: 68181 | N8: Good | O8: 5.6465753 | P8: =IF(J8<>"","DESLIGADO","ATIVO") -> DESLIGADO | Q8: =IF(N8="Excellent",5,IF(N8="Good",4,IF(N8="Satisfactory",3,0))) -> 4
A9: 00-31429110 | B9: Joshua | C9: Booth | D9: Female | E9: New York | F9: New York City | G9: Bachelor | H9: 34961 | I9: 44856 | J9: 45036 | K9: Finance | L9: Accounts Payable Specialist | M9: 54499 | N9: Good | O9: 3.4630137 | P9: =IF(J9<>"","DESLIGADO","ATIVO") -> DESLIGADO | Q9: =IF(N9="Excellent",5,IF(N9="Good",4,IF(N9="Satisfactory",3,0))) -> 4
A10: 00-30868105 | B10: Linda | C10: Wolfe | D10: Male | E10: New York | F10: New York City | G10: High School | H10: 37387 | I10: 42868 | J10: 44515 | K10: Operations | L10: Inventory Specialist | M10: 57340 | N10: Needs Improvement | O10: 8.909589 | P10: =IF(J10<>"","DESLIGADO","ATIVO") -> DESLIGADO | Q10: =IF(N10="Excellent",5,IF(N10="Good",4,IF(N10="Satisfactory",3,0))) -> 0
A11: 00-22448136 | B11: Joshua | C11: Lewis | D11: Female | E11: New York | F11: New York City | G11: Bachelor | H11: 29546 | I11: 43397 | J11: 44650 | K11: Operations | L11: Logistics Coordinator | M11: 54065 | N11: Good | O11: 7.460274 | P11: =IF(J11<>"","DESLIGADO","ATIVO") -> DESLIGADO | Q11: =IF(N11="Excellent",5,IF(N11="Good",4,IF(N11="Satisfactory",3,0))) -> 4
A12: 00-56164955 | B12: Matthew | C12: Davis | D12: Female | E12: New York | F12: New York City | G12: High School | H12: 34373 | I12: 44234 | J12: 44414 | K12: Marketing | L12: SEO Specialist | M12: 83262 | N12: Needs Improvement | O12: 5.1671233 | P12: =IF(J12<>"","DESLIGADO","ATIVO") -> DESLIGADO | Q12: =IF(N12="Excellent",5,IF(N12="Good",4,IF(N12="Satisfactory",3,0))) -> 0
A13: 00-71662963 | B13: Michael | C13: Cooper | D13: Female | E13: New York | F13: New York City | G13: High School | H13: 27145 | I13: 43933 | J13: 45319 | K13: HR | L13: Recruiter | M13: 61651 | N13: Needs Improvement | O13: 5.9917808 | P13: =IF(J13<>"","DESLIGADO","ATIVO") -> DESLIGADO | Q13: =IF(N13="Excellent",5,IF(N13="Good",4,IF(N13="Satisfactory",3,0))) -> 0
A14: 00-84093639 | B14: Lindsay | C14: Blair | D14: Male | E14: New York | F14: New York City | G14: Bachelor | H14: 24618 | I14: 42944 | J14: 43124 | K14: Operations | L14: Operations Analyst | M14: 75509 | N14: Good | O14: 8.7013699 | P14: =IF(J14<>"","DESLIGADO","ATIVO") -> DESLIGADO | Q14: =IF(N14="Excellent",5,IF(N14="Good",4,IF(N14="Satisfactory",3,0))) -> 4
A15: 00-58537831 | B15: David | C15: Nielsen | D15: Female | E15: New York | F15: New York City | G15: High School | H15: 37098 | I15: 43861 | J15: 44041 | K15: Customer Service | L15: Help Desk Technician | M15: 67011 | N15: Needs Improvement | O15: 6.1890411 | P15: =IF(J15<>"","DESLIGADO","ATIVO") -> DESLIGADO | Q15: =IF(N15="Excellent",5,IF(N15="Good",4,IF(N15="Satisfactory",3,0))) -> 0
A16: 00-16150444 | B16: Andrea | C16: Calderon | D16: Male | E16: Michigan | F16: Grand Rapids | G16: Bachelor | H16: 31919 | I16: 44802 | J16: 44982 | K16: IT | L16: IT Support Specialist | M16: 60136 | N16: Good | O16: 3.6109589 | P16: =IF(J16<>"","DESLIGADO","ATIVO") -> DESLIGADO | Q16: =IF(N16="Excellent",5,IF(N16="Good",4,IF(N16="Satisfactory",3,0))) -> 4
A17: 00-41244663 | B17: Nicole | C17: Ward | D17: Male | E17: New York | F17: New York City | G17: Bachelor | H17: 23358 | I17: 45001 | J17: 45181 | K17: Operations | L17: Logistics Coordinator | M17: 67552 | N17: Satisfactory | O17: 3.0657534 | P17: =IF(J17<>"","DESLIGADO","ATIVO") -> DESLIGADO | Q17: =IF(N17="Excellent",5,IF(N17="Good",4,IF(N17="Satisfactory",3,0))) -> 3
A18: 00-70855700 | B18: Janet | C18: Williams | D18: Male | E18: Michigan | F18: Grand Rapids | G18: Bachelor | H18: 37616 | I18: 44285 | J18: 44465 | K18: Operations | L18: Inventory Specialist | M18: 59934 | N18: Good | O18: 5.0273973 | P18: =IF(J18<>"","DESLIGADO","ATIVO") -> DESLIGADO | Q18: =IF(N18="Excellent",5,IF(N18="Good",4,IF(N18="Satisfactory",3,0))) -> 4
... A27: 00-97971488 | B27: Jeffrey | C27: Nguyen | D27: Male | E27: New York | F27: New York City | G27: Bachelor | H27: 33956 | I27: 44129 | J27: 44496 | K27: Operations | L27: Inventory Specialist | M27: 65830 | N27: Good | O27: 5.4547945 | P27: =IF(J27<>"","DESLIGADO","ATIVO") -> DESLIGADO | Q27: =IF(N27="Excellent",5,IF(N27="Good",4,IF(N27="Satisfactory",3,0))) -> 4
A28: 00-29175900 | B28: Kimberly | C28: Perez | D28: Male | E28: New York | F28: New York City | G28: Bachelor | H28: 25891 | I28: 42748 | K28: Marketing | L28: Content Creator | M28: 68419 | N28: Good | O28: 9.2383562 | P28: =IF(J28<>"","DESLIGADO","ATIVO") -> ATIVO | Q28: =IF(N28="Excellent",5,IF(N28="Good",4,IF(N28="Satisfactory",3,0))) -> 4
A29: 00-85345555 | B29: Linda | C29: Morales | D29: Male | E29: New York | F29: New York City | G29: Bachelor | H29: 34079 | I29: 43856 | J29: 44295 | K29: Sales | L29: Sales Specialist | M29: 71110 | N29: Needs Improvement | O29: 6.2027397 | P29: =IF(J29<>"","DESLIGADO","ATIVO") -> DESLIGADO | Q29: =IF(N29="Excellent",5,IF(N29="Good",4,IF(N29="Satisfactory",3,0))) -> 0
A30: 00-67503414 | B30: Jason | C30: Hahn | D30: Male | E30: Ohio | F30: Cleveland | G30: Bachelor | H30: 28515 | I30: 43076 | J30: 43255 | K30: IT | L30: System Administrator | M30: 84205 | N30: Excellent | O30: 8.339726 | P30: =IF(J30<>"","DESLIGADO","ATIVO") -> DESLIGADO | Q30: =IF(N30="Excellent",5,IF(N30="Good",4,IF(N30="Satisfactory",3,0))) -> 5
A31: 00-39436733 | B31: Jennifer | C31: Lewis | D31: Male | E31: New York | F31: New York City | G31: Master | H31: 30212 | I31: 43293 | J31: 43473 | K31: Sales | L31: Sales Specialist | M31: 67953 | N31: Good | O31: 7.7452055 | P31: =IF(J31<>"","DESLIGADO","ATIVO") -> DESLIGADO | Q31: =IF(N31="Excellent",5,IF(N31="Good",4,IF(N31="Satisfactory",3,0))) -> 4
A32: 00-76238574 | B32: Randall | C32: Rocha | D32: Male | E32: New York | F32: New York City | G32: High School | H32: 22184 | I32: 42548 | J32: 44326 | K32: IT | L32: IT Support Specialist | M32: 58445 | N32: Needs Improvement | O32: 9.7863014 | P32: =IF(J32<>"","DESLIGADO","ATIVO") -> DESLIGADO | Q32: =IF(N32="Excellent",5,IF(N32="Good",4,IF(N32="Satisfactory",3,0))) -> 0
A33: 00-24716857 | B33: Douglas | C33: Taylor | D33: Female | E33: New York | F33: New York City | G33: Bachelor | H33: 33802 | I33: 43025 | J33: 44516 | K33: Customer Service | L33: Customer Service Representative | M33: 58697 | N33: Satisfactory | O33: 8.4794521 | P33: =IF(J33<>"","DESLIGADO","ATIVO") -> DESLIGADO | Q33: =IF(N33="Excellent",5,IF(N33="Good",4,IF(N33="Satisfactory",3,0))) -> 3
A34: 00-66661351 | B34: Anna | C34: Baker | D34: Male | E34: New York | F34: New York City | G34: PhD | H34: 25700 | I34: 44058 | J34: 44882 | K34: Sales | L34: Sales Specialist | M34: 77156 | N34: Excellent | O34: 5.6493151 | P34: =IF(J34<>"","DESLIGADO","ATIVO") -> DESLIGADO | Q34: =IF(N34="Excellent",5,IF(N34="Good",4,IF(N34="Satisfactory",3,0))) -> 5
A35: 00-89978790 | B35: Ross | C35: Silva | D35: Female | E35: New York | F35: New York City | G35: Bachelor | H35: 37589 | I35: 45432 | J35: 45612 | K35: Sales | L35: Sales Specialist | M35: 81038 | N35: Excellent | O35: 1.8849315 | P35: =IF(J35<>"","DESLIGADO","ATIVO") -> DESLIGADO | Q35: =IF(N35="Excellent",5,IF(N35="Good",4,IF(N35="Satisfactory",3,0))) -> 5
A36: 00-84252722 | B36: Jeffrey | C36: Bright | D36: Male | E36: New York | F36: New York City | G36: Bachelor | H36: 29362 | I36: 42933 | J36: 43113 | K36: Finance | L36: Accounts Payable Specialist | M36: 71339 | N36: Satisfactory | O36: 8.7315068 | P36: =IF(J36<>"","DESLIGADO","ATIVO") -> DESLIGADO | Q36: =IF(N36="Excellent",5,IF(N36="Good",4,IF(N36="Satisfactory",3,0))) -> 3
A37: 00-25374874 | B37: Trevor | C37: Campos | D37: Male | E37: New York | F37: New York City | G37: Master | H37: 30366 | I37: 44896 | J37: 45076 | K37: Operations | L37: Operations Analyst | M37: 81316 | N37: Excellent | O37: 3.3534247 | P37: =IF(J37<>"","DESLIGADO","ATIVO") -> DESLIGADO | Q37: =IF(N37="Excellent",5,IF(N37="Good",4,IF(N37="Satisfactory",3,0))) -> 5
A38: 00-45812670 | B38: Daniel | C38: Burton | D38: Female | E38: New York | F38: New York City | G38: Bachelor | H38: 37065 | I38: 44869 | J38: 45336 | K38: IT | L38: Software Developer | M38: 96947 | N38: Excellent | O38: 3.4273973 | P38: =IF(J38<>"","DESLIGADO","ATIVO") -> DESLIGADO | Q38: =IF(N38="Excellent",5,IF(N38="Good",4,IF(N38="Satisfactory",3,0))) -> 5
A39: 00-49392920 | B39: Erin | C39: Carlson | D39: Male | E39: New York | F39: New York City | G39: Bachelor | H39: 30761 | I39: 43615 | J39: 44315 | K39: Operations | L39: Logistics Coordinator | M39: 67437 | N39: Excellent | O39: 6.8630137 | P39: =IF(J39<>"","DESLIGADO","ATIVO") -> DESLIGADO | Q39: =IF(N39="Excellent",5,IF(N39="Good",4,IF(N39="Satisfactory",3,0))) -> 5
A40: 00-45351479 | B40: Patrick | C40: Ferrell | D40: Female | E40: Michigan | F40: Detroit | G40: PhD | H40: 25343 | I40: 43305 | J40: 43485 | K40: Sales | L40: Sales Consultant | M40: 116328 | N40: Excellent | O40: 7.7123288 | P40: =IF(J40<>"","DESLIGADO","ATIVO") -> DESLIGADO | Q40: =IF(N40="Excellent",5,IF(N40="Good",4,IF(N40="Satisfactory",3,0))) -> 5
... A46: 00-51273847 | B46: Jennifer | C46: Stanton | D46: Male | E46: New York | F46: New York City | G46: Bachelor | H46: 21893 | I46: 43031 | J46: 43436 | K46: Customer Service | L46: Support Specialist | M46: 68635 | N46: Satisfactory | O46: 8.4630137 | P46: =IF(J46<>"","DESLIGADO","ATIVO") -> DESLIGADO | Q46: =IF(N46="Excellent",5,IF(N46="Good",4,IF(N46="Satisfactory",3,0))) -> 3
A47: 00-20570592 | B47: Guy | C47: Gaines | D47: Male | E47: New York | F47: New York City | G47: Bachelor | H47: 37544 | I47: 42708 | K47: Sales | L47: Sales Representative | M47: 80367 | N47: Satisfactory | O47: 9.3479452 | P47: =IF(J47<>"","DESLIGADO","ATIVO") -> ATIVO | Q47: =IF(N47="Excellent",5,IF(N47="Good",4,IF(N47="Satisfactory",3,0))) -> 3
A48: 00-19289546 | B48: Colleen | C48: Skinner | D48: Female | E48: New York | F48: New York City | G48: Bachelor | H48: 29921 | I48: 43297 | J48: 43477 | K48: Operations | L48: Inventory Specialist | M48: 63169 | N48: Good | O48: 7.7342466 | P48: =IF(J48<>"","DESLIGADO","ATIVO") -> DESLIGADO | Q48: =IF(N48="Excellent",5,IF(N48="Good",4,IF(N48="Satisfactory",3,0))) -> 4
A49: 00-26879290 | B49: Chelsea | C49: Hernandez | D49: Female | E49: Pennsylvania | F49: Philadelphia | G49: Master | H49: 30243 | I49: 42666 | J49: 43621 | K49: Sales | L49: Sales Consultant | M49: 71142 | N49: Good | O49: 9.4630137 | P49: =IF(J49<>"","DESLIGADO","ATIVO") -> DESLIGADO | Q49: =IF(N49="Excellent",5,IF(N49="Good",4,IF(N49="Satisfactory",3,0))) -> 4
A50: 00-32162965 | B50: Evan | C50: Ashley | D50: Male | E50: New York | F50: New York City | G50: High School | H50: 30575 | I50: 43094 | J50: 43441 | K50: Operations | L50: Inventory Specialist | M50: 58830 | N50: Needs Improvement | O50: 8.290411 | P50: =IF(J50<>"","DESLIGADO","ATIVO") -> DESLIGADO | Q50: =IF(N50="Excellent",5,IF(N50="Good",4,IF(N50="Satisfactory",3,0))) -> 0
A51: 00-38427073 | B51: Alyssa | C51: Smith | D51: Female | E51: Michigan | F51: Grand Rapids | G51: Bachelor | H51: 25682 | I51: 45417 | J51: 45597 | K51: Customer Service | L51: Customer Service Representative | M51: 66218 | N51: Satisfactory | O51: 1.9260274 | P51: =IF(J51<>"","DESLIGADO","ATIVO") -> DESLIGADO | Q51: =IF(N51="Excellent",5,IF(N51="Good",4,IF(N51="Satisfactory",3,0))) -> 3
A52: 00-36998038 | B52: Tracy | C52: Rodriguez | D52: Female | E52: New York | F52: New York City | G52: High School | H52: 29166 | I52: 44702 | J52: 44882 | K52: Marketing | L52: SEO Specialist | M52: 88887 | N52: Needs Improvement | O52: 3.8849315 | P52: =IF(J52<>"","DESLIGADO","ATIVO") -> DESLIGADO | Q52: =IF(N52="Excellent",5,IF(N52="Good",4,IF(N52="Satisfactory",3,0))) -> 0
A53: 00-97225156 | B53: Natasha | C53: Decker | D53: Male | E53: New York | F53: New York City | G53: PhD | H53: 21767 | I53: 43220 | J53: 45246 | K53: Sales | L53: Sales Consultant | M53: 72859 | N53: Excellent | O53: 7.9452055 | P53: =IF(J53<>"","DESLIGADO","ATIVO") -> DESLIGADO | Q53: =IF(N53="Excellent",5,IF(N53="Good",4,IF(N53="Satisfactory",3,0))) -> 5
A54: 00-26240908 | B54: John | C54: Allen | D54: Male | E54: New York | F54: New York City | G54: Bachelor | H54: 31062 | I54: 42956 | J54: 43136 | K54: Operations | L54: Logistics Coordinator | M54: 67630 | N54: Excellent | O54: 8.6684932 | P54: =IF(J54<>"","DESLIGADO","ATIVO") -> DESLIGADO | Q54: =IF(N54="Excellent",5,IF(N54="Good",4,IF(N54="Satisfactory",3,0))) -> 5
A55: 00-12823170 | B55: Stacey | C55: Miller | D55: Male | E55: New York | F55: New York City | G55: Bachelor | H55: 33410 | I55: 44019 | J55: 45640 | K55: Operations | L55: Inventory Specialist | M55: 61574 | N55: Excellent | O55: 5.7561644 | P55: =IF(J55<>"","DESLIGADO","ATIVO") -> DESLIGADO | Q55: =IF(N55="Excellent",5,IF(N55="Good",4,IF(N55="Satisfactory",3,0))) -> 5
A56: 00-39557077 | B56: Lisa | C56: Spence | D56: Male | E56: New York | F56: New York City | G56: Master | H56: 25805 | I56: 42211 | J56: 45278 | K56: IT | L56: Software Developer | M56: 103756 | N56: Excellent | O56: 10.709589 | P56: =IF(J56<>"","DESLIGADO","ATIVO") -> DESLIGADO | Q56: =IF(N56="Excellent",5,IF(N56="Good",4,IF(N56="Satisfactory",3,0))) -> 5
A57: 00-17901903 | B57: Katie | C57: Anderson | D57: Male | E57: New York | F57: New York City | G57: Bachelor | H57: 29581 | I57: 42920 | J57: 44559 | K57: Operations | L57: Logistics Coordinator | M57: 63227 | N57: Excellent | O57: 8.7671233 | P57: =IF(J57<>"","DESLIGADO","ATIVO") -> DESLIGADO | Q57: =IF(N57="Excellent",5,IF(N57="Good",4,IF(N57="Satisfactory",3,0))) -> 5
A58: 00-54349361 | B58: Stacey | C58: Martin | D58: Male | E58: New York | F58: New York City | G58: High School | H58: 34055 | I58: 42574 | K58: Operations | L58: Inventory Specialist | M58: 63680 | N58: Needs Improvement | O58: 9.7150685 | P58: =IF(J58<>"","DESLIGADO","ATIVO") -> ATIVO | Q58: =IF(N58="Excellent",5,IF(N58="Good",4,IF(N58="Satisfactory",3,0))) -> 0
A59: 00-99788677 | B59: Monique | C59: Henderson | D59: Female | E59: New York | F59: New York City | G59: Bachelor | H59: 24647 | I59: 43548 | J59: 43728 | K59: Customer Service | L59: Help Desk Technician | M59: 90880 | N59: Satisfactory | O59: 7.0465753 | P59: =IF(J59<>"","DESLIGADO","ATIVO") -> DESLIGADO | Q59: =IF(N59="Excellent",5,IF(N59="Good",4,IF(N59="Satisfactory",3,0))) -> 3
A60: 00-86644106 | B60: Sarah | C60: Campos | D60: Female | E60: Pennsylvania | F60: Philadelphia | G60: High School | H60: 30475 | I60: 44098 | J60: 44806 | K60: Marketing | L60: Content Creator | M60: 52954 | N60: Excellent | O60: 5.539726 | P60: =IF(J60<>"","DESLIGADO","ATIVO") -> DESLIGADO | Q60: =IF(N60="Excellent",5,IF(N60="Good",4,IF(N60="Satisfactory",3,0))) -> 5
A61: 00-73481353 | B61: James | C61: Collins | D61: Female | E61: New York | F61: New York City | G61: Bachelor | H61: 28261 | I61: 42996 | J61: 43175 | K61: Operations | L61: Inventory Specialist | M61: 64475 | N61: Good | O61: 8.5589041 | P61: =IF(J61<>"","DESLIGADO","ATIVO") -> DESLIGADO | Q61: =IF(N61="Excellent",5,IF(N61="Good",4,IF(N61="Satisfactory",3,0))) -> 4
A62: 00-23009833 | B62: Debra | C62: Kim | D62: Female | E62: Pennsylvania | F62: Allentown | G62: PhD | H62: 29247 | I62: 44763 | J62: 44943 | K62: Sales | L62: Sales Specialist | M62: 93238 | N62: Excellent | O62: 3.7178082 | P62: =IF(J62<>"","DESLIGADO","ATIVO") -> DESLIGADO | Q62: =IF(N62="Excellent",5,IF(N62="Good",4,IF(N62="Satisfactory",3,0))) -> 5
A63: 00-65177213 | B63: Shannon | C63: Wright | D63: Female | E63: Michigan | F63: Grand Rapids | G63: High School | H63: 37594 | I63: 43490 | J63: 44907 | K63: Operations | L63: Inventory Specialist | M63: 58713 | N63: Needs Improvement | O63: 7.2054795 | P63: =IF(J63<>"","DESLIGADO","ATIVO") -> DESLIGADO | Q63: =IF(N63="Excellent",5,IF(N63="Good",4,IF(N63="Satisfactory",3,0))) -> 0
A64: 00-97705310 | B64: Matthew | C64: Chapman | D64: Female | E64: New York | F64: New York City | G64: Bachelor | H64: 25465 | I64: 45381 | J64: 45561 | K64: IT | L64: Software Developer | M64: 91896 | N64: Needs Improvement | O64: 2.0246575 | P64: =IF(J64<>"","DESLIGADO","ATIVO") -> DESLIGADO | Q64: =IF(N64="Excellent",5,IF(N64="Good",4,IF(N64="Satisfactory",3,0))) -> 0
A65: 00-64038913 | B65: Brianna | C65: Smith | D65: Male | E65: New York | F65: New York City | G65: Bachelor | H65: 27047 | I65: 44836 | J65: 45016 | K65: Operations | L65: Inventory Specialist | M65: 71608 | N65: Excellent | O65: 3.5178082 | P65: =IF(J65<>"","DESLIGADO","ATIVO") -> DESLIGADO | Q65: =IF(N65="Excellent",5,IF(N65="Good",4,IF(N65="Satisfactory",3,0))) -> 5
A66: 00-35714784 | B66: Crystal | C66: Perez | D66: Female | E66: New York | F66: New York City | G66: Bachelor | H66: 30504 | I66: 43087 | J66: 43267 | K66: Finance | L66: Financial Analyst | M66: 71404 | N66: Satisfactory | O66: 8.309589 | P66: =IF(J66<>"","DESLIGADO","ATIVO") -> DESLIGADO | Q66: =IF(N66="Excellent",5,IF(N66="Good",4,IF(N66="Satisfactory",3,0))) -> 3
A67: 00-66623995 | B67: Anthony | C67: Rivera | D67: Male | E67: New York | F67: New York City | G67: Bachelor | H67: 33638 | I67: 42935 | J67: 44332 | K67: Operations | L67: Logistics Coordinator | M67: 59423 | N67: Good | O67: 8.7260274 | P67: =IF(J67<>"","DESLIGADO","ATIVO") -> DESLIGADO | Q67: =IF(N67="Excellent",5,IF(N67="Good",4,IF(N67="Satisfactory",3,0))) -> 4
A68: 00-20117988 | B68: John | C68: Caldwell | D68: Female | E68: New York | F68: New York City | G68: Bachelor | H68: 30243 | I68: 43549 | J68: 43729 | K68: Operations | L68: Operations Analyst | M68: 64183 | N68: Needs Improvement | O68: 7.0438356 | P68: =IF(J68<>"","DESLIGADO","ATIVO") -> DESLIGADO | Q68: =IF(N68="Excellent",5,IF(N68="Good",4,IF(N68="Satisfactory",3,0))) -> 0
A69: 00-16789850 | B69: Amber | C69: Cummings | D69: Male | E69: New York | F69: New York City | G69: Master | H69: 31604 | I69: 44904 | J69: 45084 | K69: Operations | L69: Operations Analyst | M69: 76824 | N69: Excellent | O69: 3.3315068 | P69: =IF(J69<>"","DESLIGADO","ATIVO") -> DESLIGADO | Q69: =IF(N69="Excellent",5,IF(N69="Good",4,IF(N69="Satisfactory",3,0))) -> 5
A70: 00-11980765 | B70: Ashley | C70: Kennedy | D70: Female | E70: New York | F70: New York City | G70: Bachelor | H70: 37704 | I70: 43404 | J70: 43584 | K70: Finance | L70: Accountant | M70: 54093 | N70: Satisfactory | O70: 7.4410959 | P70: =IF(J70<>"","DESLIGADO","ATIVO") -> DESLIGADO | Q70: =IF(N70="Excellent",5,IF(N70="Good",4,IF(N70="Satisfactory",3,0))) -> 3
... A79: 00-81286543 | B79: Charles | C79: Morton | D79: Male | E79: New York | F79: New York City | G79: Bachelor | H79: 30937 | I79: 43068 | J79: 43248 | K79: Finance | L79: Accountant | M79: 78616 | N79: Satisfactory | O79: 8.3616438 | P79: =IF(J79<>"","DESLIGADO","ATIVO") -> DESLIGADO | Q79: =IF(N79="Excellent",5,IF(N79="Good",4,IF(N79="Satisfactory",3,0))) -> 3
A80: 00-34941004 | B80: Andrea | C80: Williams | D80: Male | E80: New York | F80: New York City | G80: High School | H80: 22035 | I80: 42579 | K80: Operations | L80: Inventory Specialist | M80: 57716 | N80: Needs Improvement | O80: 9.7013699 | P80: =IF(J80<>"","DESLIGADO","ATIVO") -> ATIVO | Q80: =IF(N80="Excellent",5,IF(N80="Good",4,IF(N80="Satisfactory",3,0))) -> 0
A81: 00-41568532 | B81: Mary | C81: Novak | D81: Female | E81: New York | F81: New York City | G81: Bachelor | H81: 29749 | I81: 43825 | J81: 44005 | K81: Operations | L81: Logistics Coordinator | M81: 61198 | N81: Satisfactory | O81: 6.2876712 | P81: =IF(J81<>"","DESLIGADO","ATIVO") -> DESLIGADO | Q81: =IF(N81="Excellent",5,IF(N81="Good",4,IF(N81="Satisfactory",3,0))) -> 3
A82: 00-87701200 | B82: Karen | C82: Young | D82: Male | E82: New York | F82: New York City | G82: Bachelor | H82: 37065 | I82: 43988 | J82: 44168 | K82: IT | L82: IT Support Specialist | M82: 58331 | N82: Excellent | O82: 5.8410959 | P82: =IF(J82<>"","DESLIGADO","ATIVO") -> DESLIGADO | Q82: =IF(N82="Excellent",5,IF(N82="Good",4,IF(N82="Satisfactory",3,0))) -> 5
A83: 00-66267415 | B83: Todd | C83: Lewis | D83: Female | E83: Ohio | F83: Cincinnati | G83: Bachelor | H83: 24162 | I83: 44717 | J83: 45602 | K83: Operations | L83: Logistics Coordinator | M83: 62398 | N83: Good | O83: 3.8438356 | P83: =IF(J83<>"","DESLIGADO","ATIVO") -> DESLIGADO | Q83: =IF(N83="Excellent",5,IF(N83="Good",4,IF(N83="Satisfactory",3,0))) -> 4
A84: 00-52462441 | B84: Rachel | C84: Martin | D84: Male | E84: New York | F84: New York City | G84: Bachelor | H84: 30919 | I84: 45292 | J84: 45472 | K84: Sales | L84: Sales Consultant | M84: 94930 | N84: Excellent | O84: 2.2684932 | P84: =IF(J84<>"","DESLIGADO","ATIVO") -> DESLIGADO | Q84: =IF(N84="Excellent",5,IF(N84="Good",4,IF(N84="Satisfactory",3,0))) -> 5
A85: 00-52169044 | B85: Tricia | C85: Baker | D85: Female | E85: New York | F85: New York City | G85: Bachelor | H85: 35972 | I85: 43040 | J85: 44261 | K85: Customer Service | L85: Customer Service Representative | M85: 59179 | N85: Good | O85: 8.4383562 | P85: =IF(J85<>"","DESLIGADO","ATIVO") -> DESLIGADO | Q85: =IF(N85="Excellent",5,IF(N85="Good",4,IF(N85="Satisfactory",3,0))) -> 4
A86: 00-96637649 | B86: Kristen | C86: Mitchell | D86: Male | E86: North Carolina | F86: Greensboro | G86: Bachelor | H86: 27896 | I86: 43006 | J86: 45328 | K86: Operations | L86: Logistics Coordinator | M86: 74555 | N86: Good | O86: 8.5315068 | P86: =IF(J86<>"","DESLIGADO","ATIVO") -> DESLIGADO | Q86: =IF(N86="Excellent",5,IF(N86="Good",4,IF(N86="Satisfactory",3,0))) -> 4
A87: 00-19736572 | B87: Susan | C87: Cowan | D87: Male | E87: New York | F87: New York City | G87: PhD | H87: 32783 | I87: 42220 | K87: Sales | L87: Sales Manager | M87: 74371 | N87: Excellent | O87: 10.684932 | P87: =IF(J87<>"","DESLIGADO","ATIVO") -> ATIVO | Q87: =IF(N87="Excellent",5,IF(N87="Good",4,IF(N87="Satisfactory",3,0))) -> 5
A88: 00-23419256 | B88: Dorothy | C88: Tucker | D88: Female | E88: New York | F88: New York City | G88: Bachelor | H88: 33102 | I88: 42443 | J88: 42623 | K88: Marketing | L88: SEO Specialist | M88: 81253 | N88: Excellent | O88: 10.073973 | P88: =IF(J88<>"","DESLIGADO","ATIVO") -> DESLIGADO | Q88: =IF(N88="Excellent",5,IF(N88="Good",4,IF(N88="Satisfactory",3,0))) -> 5
A89: 00-45594597 | B89: Kenneth | C89: Novak | D89: Female | E89: New York | F89: New York City | G89: High School | H89: 32416 | I89: 42960 | J89: 43900 | K89: Customer Service | L89: Customer Service Representative | M89: 56922 | N89: Needs Improvement | O89: 8.6575342 | P89: =IF(J89<>"","DESLIGADO","ATIVO") -> DESLIGADO | Q89: =IF(N89="Excellent",5,IF(N89="Good",4,IF(N89="Satisfactory",3,0))) -> 0
A90: 00-42787299 | B90: Jill | C90: Brown | D90: Female | E90: New York | F90: New York City | G90: Bachelor | H90: 30115 | I90: 43222 | J90: 43902 | K90: Marketing | L90: Content Creator | M90: 65108 | N90: Satisfactory | O90: 7.939726 | P90: =IF(J90<>"","DESLIGADO","ATIVO") -> DESLIGADO | Q90: =IF(N90="Excellent",5,IF(N90="Good",4,IF(N90="Satisfactory",3,0))) -> 3
A91: 00-82909480 | B91: Brian | C91: Silva | D91: Female | E91: New York | F91: New York City | G91: Bachelor | H91: 27698 | I91: 44757 | J91: 44937 | K91: Operations | L91: Logistics Coordinator | M91: 61958 | N91: Good | O91: 3.7342466 | P91: =IF(J91<>"","DESLIGADO","ATIVO") -> DESLIGADO | Q91: =IF(N91="Excellent",5,IF(N91="Good",4,IF(N91="Satisfactory",3,0))) -> 4
A92: 00-97775215 | B92: Samantha | C92: Schmidt | D92: Female | E92: New York | F92: New York City | G92: Bachelor | H92: 36171 | I92: 43853 | J92: 44772 | K92: Customer Service | L92: Support Specialist | M92: 55038 | N92: Good | O92: 6.2109589 | P92: =IF(J92<>"","DESLIGADO","ATIVO") -> DESLIGADO | Q92: =IF(N92="Excellent",5,IF(N92="Good",4,IF(N92="Satisfactory",3,0))) -> 4
A93: 00-84437458 | B93: Susan | C93: Miller | D93: Female | E93: New York | F93: New York City | G93: Master | H93: 37293 | I93: 42808 | J93: 45036 | K93: HR | L93: HR Coordinator | M93: 63666 | N93: Excellent | O93: 9.0739726 | P93: =IF(J93<>"","DESLIGADO","ATIVO") -> DESLIGADO | Q93: =IF(N93="Excellent",5,IF(N93="Good",4,IF(N93="Satisfactory",3,0))) -> 5
A94: 00-28024248 | B94: Casey | C94: Jones | D94: Female | E94: New York | F94: New York City | G94: High School | H94: 29168 | I94: 43070 | J94: 44238 | K94: Customer Service | L94: Help Desk Technician | M94: 58264 | N94: Excellent | O94: 8.3561644 | P94: =IF(J94<>"","DESLIGADO","ATIVO") -> DESLIGADO | Q94: =IF(N94="Excellent",5,IF(N94="Good",4,IF(N94="Satisfactory",3,0))) -> 5
A95: 00-84252420 | B95: Joe | C95: Wilson | D95: Male | E95: New York | F95: New York City | G95: Bachelor | H95: 37658 | I95: 43081 | J95: 44831 | K95: Sales | L95: Sales Representative | M95: 65128 | N95: Satisfactory | O95: 8.3260274 | P95: =IF(J95<>"","DESLIGADO","ATIVO") -> DESLIGADO | Q95: =IF(N95="Excellent",5,IF(N95="Good",4,IF(N95="Satisfactory",3,0))) -> 3
A96: 00-38270233 | B96: Ashley | C96: Riley | D96: Male | E96: New York | F96: New York City | G96: Master | H96: 24689 | I96: 44577 | J96: 44757 | K96: Sales | L96: Sales Consultant | M96: 69316 | N96: Excellent | O96: 4.2273973 | P96: =IF(J96<>"","DESLIGADO","ATIVO") -> DESLIGADO | Q96: =IF(N96="Excellent",5,IF(N96="Good",4,IF(N96="Satisfactory",3,0))) -> 5
A97: 00-95125977 | B97: Christine | C97: Barnes | D97: Male | E97: New York | F97: New York City | G97: High School | H97: 33899 | I97: 42962 | J97: 43142 | K97: Operations | L97: Inventory Specialist | M97: 56431 | N97: Needs Improvement | O97: 8.6520548 | P97: =IF(J97<>"","DESLIGADO","ATIVO") -> DESLIGADO | Q97: =IF(N97="Excellent",5,IF(N97="Good",4,IF(N97="Satisfactory",3,0))) -> 0
A98: 00-43704923 | B98: Annette | C98: Stewart | D98: Male | E98: New York | F98: New York City | G98: Bachelor | H98: 35600 | I98: 45028 | J98: 45208 | K98: Sales | L98: Sales Representative | M98: 79043 | N98: Good | O98: 2.9917808 | P98: =IF(J98<>"","DESLIGADO","ATIVO") -> DESLIGADO | Q98: =IF(N98="Excellent",5,IF(N98="Good",4,IF(N98="Satisfactory",3,0))) -> 4
A99: 00-95132217 | B99: James | C99: Moran | D99: Female | E99: New York | F99: New York City | G99: Bachelor | H99: 32445 | I99: 43558 | J99: 45538 | K99: Marketing | L99: Marketing Coordinator | M99: 59137 | N99: Good | O99: 7.0191781 | P99: =IF(J99<>"","DESLIGADO","ATIVO") -> DESLIGADO | Q99: =IF(N99="Excellent",5,IF(N99="Good",4,IF(N99="Satisfactory",3,0))) -> 4
... A103: 00-30005727 | B103: Yolanda | C103: Ferrell | D103: Male | E103: New York | F103: New York City | G103: Master | H103: 30229 | I103: 43859 | J103: 44039 | K103: Operations | L103: Operations Analyst | M103: 55106 | N103: Excellent | O103: 6.1945205 | P103: =IF(J103<>"","DESLIGADO","ATIVO") -> DESLIGADO | Q103: =IF(N103="Excellent",5,IF(N103="Good",4,IF(N103="Satisfactory",3,0))) -> 5
A104: 00-84158663 | B104: Amanda | C104: Wagner | D104: Male | E104: New York | F104: New York City | G104: Bachelor | H104: 32052 | I104: 42787 | K104: IT | L104: Software Developer | M104: 88492 | N104: Good | O104: 9.1315068 | P104: =IF(J104<>"","DESLIGADO","ATIVO") -> ATIVO | Q104: =IF(N104="Excellent",5,IF(N104="Good",4,IF(N104="Satisfactory",3,0))) -> 4
A105: 00-51373735 | B105: Sarah | C105: Ibarra | D105: Male | E105: New York | F105: New York City | G105: High School | H105: 27969 | I105: 43442 | J105: 44311 | K105: Customer Service | L105: Help Desk Technician | M105: 82441 | N105: Needs Improvement | O105: 7.3369863 | P105: =IF(J105<>"","DESLIGADO","ATIVO") -> DESLIGADO | Q105: =IF(N105="Excellent",5,IF(N105="Good",4,IF(N105="Satisfactory",3,0))) -> 0
A106: 00-38195995 | B106: John | C106: Mitchell | D106: Male | E106: Michigan | F106: Warren | G106: Bachelor | H106: 22916 | I106: 44732 | J106: 44912 | K106: Finance | L106: Accountant | M106: 85555 | N106: Good | O106: 3.8027397 | P106: =IF(J106<>"","DESLIGADO","ATIVO") -> DESLIGADO | Q106: =IF(N106="Excellent",5,IF(N106="Good",4,IF(N106="Satisfactory",3,0))) -> 4
A107: 00-57469942 | B107: Martha | C107: Warner | D107: Female | E107: New York | F107: New York City | G107: Bachelor | H107: 32721 | I107: 42973 | J107: 43153 | K107: Sales | L107: Sales Consultant | M107: 64372 | N107: Satisfactory | O107: 8.6219178 | P107: =IF(J107<>"","DESLIGADO","ATIVO") -> DESLIGADO | Q107: =IF(N107="Excellent",5,IF(N107="Good",4,IF(N107="Satisfactory",3,0))) -> 3
A108: 00-30743797 | B108: Tonya | C108: Roman | D108: Female | E108: Michigan | F108: Grand Rapids | G108: Bachelor | H108: 26007 | I108: 43305 | J108: 43485 | K108: Customer Service | L108: Customer Service Representative | M108: 63278 | N108: Good | O108: 7.7123288 | P108: =IF(J108<>"","DESLIGADO","ATIVO") -> DESLIGADO | Q108: =IF(N108="Excellent",5,IF(N108="Good",4,IF(N108="Satisfactory",3,0))) -> 4
A109: 00-31810617 | B109: Alan | C109: Montoya | D109: Male | E109: Virginia | F109: Virginia Beach | G109: Bachelor | H109: 35829 | I109: 45408 | J109: 45588 | K109: Marketing | L109: Content Creator | M109: 65358 | N109: Needs Improvement | O109: 1.9506849 | P109: =IF(J109<>"","DESLIGADO","ATIVO") -> DESLIGADO | Q109: =IF(N109="Excellent",5,IF(N109="Good",4,IF(N109="Satisfactory",3,0))) -> 0
A110: 00-13326769 | B110: Sarah | C110: Garcia | D110: Male | E110: Michigan | F110: Grand Rapids | G110: Bachelor | H110: 30653 | I110: 43077 | J110: 43257 | K110: IT | L110: System Administrator | M110: 77267 | N110: Good | O110: 8.3369863 | P110: =IF(J110<>"","DESLIGADO","ATIVO") -> DESLIGADO | Q110: =IF(N110="Excellent",5,IF(N110="Good",4,IF(N110="Satisfactory",3,0))) -> 4
A111: 00-65259205 | B111: Dennis | C111: Wilson | D111: Female | E111: New York | F111: New York City | G111: Bachelor | H111: 37323 | I111: 44968 | J111: 45148 | K111: Sales | L111: Sales Representative | M111: 51865 | N111: Good | O111: 3.1561644 | P111: =IF(J111<>"","DESLIGADO","ATIVO") -> DESLIGADO | Q111: =IF(N111="Excellent",5,IF(N111="Good",4,IF(N111="Satisfactory",3,0))) -> 4
A112: 00-43308443 | B112: Julia | C112: Moore | D112: Male | E112: New York | F112: New York City | G112: Master | H112: 25834 | I112: 42845 | J112: 45645 | K112: IT | L112: System Administrator | M112: 92780 | N112: Excellent | O112: 8.9726027 | P112: =IF(J112<>"","DESLIGADO","ATIVO") -> DESLIGADO | Q112: =IF(N112="Excellent",5,IF(N112="Good",4,IF(N112="Satisfactory",3,0))) -> 5
A113: 00-61343880 | B113: Cassandra | C113: Robbins | D113: Female | E113: Pennsylvania | F113: Allentown | G113: Bachelor | H113: 33729 | I113: 45006 | J113: 45186 | K113: Customer Service | L113: Customer Service Representative | M113: 52588 | N113: Good | O113: 3.0520548 | P113: =IF(J113<>"","DESLIGADO","ATIVO") -> DESLIGADO | Q113: =IF(N113="Excellent",5,IF(N113="Good",4,IF(N113="Satisfactory",3,0))) -> 4
A114: 00-36786211 | B114: Grace | C114: Farrell | D114: Female | E114: Michigan | F114: Detroit | G114: Bachelor | H114: 26473 | I114: 45123 | J114: 45303 | K114: Operations | L114: Inventory Specialist | M114: 64186 | N114: Good | O114: 2.7315068 | P114: =IF(J114<>"","DESLIGADO","ATIVO") -> DESLIGADO | Q114: =IF(N114="Excellent",5,IF(N114="Good",4,IF(N114="Satisfactory",3,0))) -> 4
A115: 00-50962024 | B115: Tracy | C115: Whitehead | D115: Male | E115: New York | F115: New York City | G115: High School | H115: 28636 | I115: 43064 | J115: 43243 | K115: Operations | L115: Inventory Specialist | M115: 61124 | N115: Needs Improvement | O115: 8.3726027 | P115: =IF(J115<>"","DESLIGADO","ATIVO") -> DESLIGADO | Q115: =IF(N115="Excellent",5,IF(N115="Good",4,IF(N115="Satisfactory",3,0))) -> 0
A116: 00-13176186 | B116: Brent | C116: Walters | D116: Female | E116: New York | F116: New York City | G116: High School | H116: 30149 | I116: 44884 | J116: 45064 | K116: HR | L116: Recruiter | M116: 65797 | N116: Needs Improvement | O116: 3.3863014 | P116: =IF(J116<>"","DESLIGADO","ATIVO") -> DESLIGADO | Q116: =IF(N116="Excellent",5,IF(N116="Good",4,IF(N116="Satisfactory",3,0))) -> 0
... A153: 00-79967676 | B153: William | C153: Estrada | D153: Male | E153: New York | F153: New York City | G153: Bachelor | H153: 31110 | I153: 43592 | J153: 44067 | K153: Operations | L153: Operations Manager | M153: 109148 | N153: Good | O153: 6.9260274 | P153: =IF(J153<>"","DESLIGADO","ATIVO") -> DESLIGADO | Q153: =IF(N153="Excellent",5,IF(N153="Good",4,IF(N153="Satisfactory",3,0))) -> 4
A154: 00-69038700 | B154: Richard | C154: Phillips | D154: Female | E154: New York | F154: New York City | G154: Bachelor | H154: 37168 | I154: 42419 | K154: Operations | L154: Operations Analyst | M154: 77304 | N154: Satisfactory | O154: 10.139726 | P154: =IF(J154<>"","DESLIGADO","ATIVO") -> ATIVO | Q154: =IF(N154="Excellent",5,IF(N154="Good",4,IF(N154="Satisfactory",3,0))) -> 3
A155: 00-46468984 | B155: James | C155: Ortega | D155: Male | E155: New York | F155: New York City | G155: Bachelor | H155: 29534 | I155: 43248 | J155: 45425 | K155: Sales | L155: Sales Specialist | M155: 71634 | N155: Satisfactory | O155: 7.8684932 | P155: =IF(J155<>"","DESLIGADO","ATIVO") -> DESLIGADO | Q155: =IF(N155="Excellent",5,IF(N155="Good",4,IF(N155="Satisfactory",3,0))) -> 3
A156: 00-28572252 | B156: Erica | C156: Orr | D156: Male | E156: New York | F156: New York City | G156: Bachelor | H156: 32463 | I156: 42975 | J156: 44871 | K156: IT | L156: IT Support Specialist | M156: 73488 | N156: Satisfactory | O156: 8.6164384 | P156: =IF(J156<>"","DESLIGADO","ATIVO") -> DESLIGADO | Q156: =IF(N156="Excellent",5,IF(N156="Good",4,IF(N156="Satisfactory",3,0))) -> 3
A157: 00-30509175 | B157: Ashley | C157: Sullivan | D157: Male | E157: New York | F157: New York City | G157: High School | H157: 30231 | I157: 44885 | J157: 45065 | K157: Operations | L157: Inventory Specialist | M157: 61678 | N157: Needs Improvement | O157: 3.3835616 | P157: =IF(J157<>"","DESLIGADO","ATIVO") -> DESLIGADO | Q157: =IF(N157="Excellent",5,IF(N157="Good",4,IF(N157="Satisfactory",3,0))) -> 0
A158: 00-64707061 | B158: Aaron | C158: Mitchell | D158: Female | E158: New York | F158: New York City | G158: Bachelor | H158: 33747 | I158: 43267 | J158: 43447 | K158: IT | L158: Software Developer | M158: 94594 | N158: Satisfactory | O158: 7.8164384 | P158: =IF(J158<>"","DESLIGADO","ATIVO") -> DESLIGADO | Q158: =IF(N158="Excellent",5,IF(N158="Good",4,IF(N158="Satisfactory",3,0))) -> 3
A159: 00-18357162 | B159: Kristi | C159: Lawson | D159: Male | E159: Michigan | F159: Detroit | G159: Bachelor | H159: 24874 | I159: 42861 | K159: Operations | L159: Inventory Specialist | M159: 76197 | N159: Satisfactory | O159: 8.9287671 | P159: =IF(J159<>"","DESLIGADO","ATIVO") -> ATIVO | Q159: =IF(N159="Excellent",5,IF(N159="Good",4,IF(N159="Satisfactory",3,0))) -> 3
A160: 00-88393811 | B160: Steven | C160: Ramos | D160: Female | E160: New York | F160: New York City | G160: Bachelor | H160: 34835 | I160: 45374 | J160: 45554 | K160: Operations | L160: Logistics Coordinator | M160: 60859 | N160: Satisfactory | O160: 2.0438356 | P160: =IF(J160<>"","DESLIGADO","ATIVO") -> DESLIGADO | Q160: =IF(N160="Excellent",5,IF(N160="Good",4,IF(N160="Satisfactory",3,0))) -> 3
...

Sheet ANÁLISE
A1: TOTAL COLABORADORES | B1: TOTAL DE DESLIGADOS | C1: TURNOVER | D1: MÉDIA DE DESEMPENHO | E1: TEMPO MÉDIO DE EMPRESA
A2: =COUNTA(Tabela1[[#This Row],[Employee_ID]]:'ADEQUAÇÃO'!A8951) -> 8950 | B2: =COUNTIF(Tabela1[[#This Row],[Termdate]]:'ADEQUAÇÃO'!J8951,"<>") -> 966 | C2: =COUNTIF(ADEQUAÇÃO!J2:J8951,"<>")/COUNTA(ADEQUAÇÃO!A2:A8951) -> 0.10793296 | D2: =AVERAGE(Tabela1[[#This Row],[Performance Score ]]:'ADEQUAÇÃO'!Q8951) -> 3.3939665 | E2: =AVERAGE(Tabela1[[#This Row],[Tenure]]:'ADEQUAÇÃO'!O8951)/365 -> 0.016814762
Q4: Rótulos de Linha | R4: Colaboradores por Departamento
Q5: Operations | R5: 2718
Q6: Sales | R6: 1835
Q7: Customer Service | R7: 1673
Q8: IT | R8: 1382
Q9: Marketing | R9: 718
Q10: Finance | R10: 452
Q11: HR | R11: 172
Q12: Total Geral | R12: 8950
Q15: Termdate | R15: (Vários itens)
Q17: Rótulos de Linha | R17: Turnover por Departamento
Q18: Operations | R18: 289
Q19: Sales | R19: 201
Q20: Customer Service | R20: 184
Q21: IT | R21: 139
Q22: Marketing | R22: 70
Q23: Finance | R23: 63
Q24: HR | R24: 20
Q25: Total Geral | R25: 966
Q31: Rótulos de Linha | R31: Desempenho Médio por Departamento
Q32: Sales | R32: 3.7100817
Q33: Finance | R33: 3.6128319
Q34: IT | R34: 3.4565847
Q35: Operations | R35: 3.3863135
Q36: HR | R36: 3.3837209
Q37: Marketing | R37: 3.1657382
Q38: Customer Service | R38: 3.0478183
Q39: Total Geral | R39: 3.3939665
Q45: Rótulos de Linha | R45: Tempo Médio de Empresa por Departamento
Q46: Sales | R46: 6.2173267
Q47: Finance | R47: 6.1745666
Q48: IT | R48: 6.1524176
Q49: Operations | R49: 6.1209522
Q50: Marketing | R50: 6.100248
Q51: Customer Service | R51: 6.0917079
Q52: HR | R52: 5.9251832
Q53: Total Geral | R53: 6.1373882

Sheet DASHBOARD
A1: Dashboard de RH | People Analytics
A2: TOTAL COLABORADORES | B2: TOTAL DE DESLIGADOS | C2: TURNOVER | D2: MÉDIA DE DESEMPENHO | E2: TEMPO MÉDIO DE EMPRESA
A3: =COUNTA(Tabela1[[#This Row],[Employee_ID]]:'ADEQUAÇÃO'!A8952) -> 8949 | B3: =COUNTIF(Tabela1[[#This Row],[Termdate]]:'ADEQUAÇÃO'!J8952,"<>") -> 965 | C3: =COUNTIF(ADEQUAÇÃO!J3:J8952,"<>")/COUNTA(ADEQUAÇÃO!A3:A8952) -> 0.10783328 | D3: =AVERAGE(Tabela1[[#This Row],[Performance Score ]]:'ADEQUAÇÃO'!Q8952) -> 3.3943457 | E3: =AVERAGE(Tabela1[[#This Row],[Tenure]]:'ADEQUAÇÃO'!O8952) -> 6.1369584
